docker_amend.py
docker_amend-0.1.2.dist-info/entry_points.txt
docker_amend-0.1.2.dist-info/WHEEL
docker_amend-0.1.2.dist-info/METADATA
docker_amend-0.1.2.dist-info/RECORD
