Metadata-Version: 2.1
Name: docker-amend
Version: 0.1.2
Summary: Amend Docker images by running a command in a separate layer.
Home-page: https://gitlab.com/notpushkin/docker-amend
License: ISC
Author: Alexander Pushkov
Author-email: alexander@notpushk.in
Requires-Python: >=3.7,<4.0
Classifier: License :: OSI Approved
Classifier: Programming Language :: Python :: 3
Classifier: Programming Language :: Python :: 3.7
Classifier: Programming Language :: Python :: 3.8
Requires-Dist: docker (>=4.2.0,<5.0.0)
Requires-Dist: typer (>=0.3.2,<0.4.0)
